{"cameraMode":{"drawMode":0,"name":"Shaded","section":"Shading Mode"},"sceneLighting":false,"audioPlay":false,"sceneViewState":{"m_AlwaysRefresh":false,"showFog":true,"showSkybox":false,"showFlares":true,"showImageEffects":true,"showParticleSystems":true,"showVisualEffectGraphs":true,"m_FxEnabled":false},"in2DMode":false,"pivot":{"x":-4.788667678833008,"y":5.553692817687988,"z":-10.243486404418946},"rotation":{"x":-0.29081255197525027,"y":-0.2320500612258911,"z":0.07292661815881729,"w":-0.925346851348877},"size":1.6271321773529053,"orthographic":false}